{
  "92000": {
    "id": 92000,
    "name": "踏入未知",
    "description": "你第一次踏入地下城，黑暗的甬道中传来远古的低语，冒险的序幕就此拉开。",
    "grade": 0,
    "hide": 0,
    "condition": "FDLV >= 1"
  },
  "92001": {
    "id": 92001,
    "name": "地城征服者",
    "description": "你已征服一百层地下城，深渊的尽头见证了你不可动摇的意志与力量。",
    "grade": 2,
    "hide": 0,
    "condition": "FDLV >= 100"
  },
  "92002": {
    "id": 92002,
    "name": "屠龙者",
    "description": "你亲手斩下古龙的头颅，龙血浸染铠甲，你的名字被游吟诗人传唱于诸王国。",
    "grade": 2,
    "hide": 0,
    "condition": "MYTHC >= 1"
  },
  "92003": {
    "id": 92003,
    "name": "贤者之智",
    "description": "你的智慧超越了凡俗，魔法学院的大贤者为你戴上水晶冠，称你为行走的图书馆。",
    "grade": 1,
    "hide": 0,
    "condition": "HINT >= 120"
  },
  "92004": {
    "id": 92004,
    "name": "富可敌国",
    "description": "你的财富足以买下一整个王国，冒险者公会的金库在你眼中不过是一个零钱袋。",
    "grade": 2,
    "hide": 0,
    "condition": "HMNY >= 1000000"
  },
  "92005": {
    "id": 92005,
    "name": "骑士荣耀",
    "description": "国王在万众瞩目下将剑搭于你的肩头，你从此以骑士之名守护这片大陆的荣光。",
    "grade": 1,
    "hide": 0,
    "condition": "SUM >= 5000"
  },
  "92006": {
    "id": 92006,
    "name": "不死鸟",
    "description": "死亡曾将你拥入怀抱，但你从灰烬中归来，灵魂燃烧着不灭的火焰。",
    "grade": 2,
    "hide": 1,
    "condition": "MYTHC >= 2 AND HSPR >= 80"
  },
  "92007": {
    "id": 92007,
    "name": "弑神者",
    "description": "你以凡人之躯挑战神明，神血染红了天穹，旧时代的帷幕在你的剑下坠落。",
    "grade": 3,
    "hide": 1,
    "condition": "MYTHC >= 4"
  },
  "92008": {
    "id": 92008,
    "name": "命运主宰",
    "description": "你的魅力、智慧、力量与精神都达到了凡人的巅峰，连诸神都不再敢轻易拨弄你的命运之线。",
    "grade": 3,
    "hide": 1,
    "condition": "HCHR >= 100 AND HINT >= 100 AND HSTR >= 100 AND HSPR >= 100"
  },
  "92009": {
    "id": 92009,
    "name": "传奇不朽",
    "description": "你活过了整整一百二十个春秋，见证了帝国的兴衰与巨龙的陨落，终成会走动的史诗。",
    "grade": 2,
    "hide": 0,
    "condition": "HAGE >= 120"
  },
  "92010": {
    "id": 92010,
    "name": "不朽传说",
    "description": "你的名字被吟游诗人传唱千年——享年九十载，凡人中已近半神。",
    "grade": 3,
    "hide": 0,
    "condition": "HAGE >= 90"
  },
  "92011": {
    "id": 92011,
    "name": "殉道者",
    "description": "英年早逝的星光，在黎明前坠落。你未满二十便踏入冥河，却点燃了后世传说的火种。",
    "grade": 2,
    "hide": 1,
    "condition": "HAGE <= 20"
  },
  "92012": {
    "id": 92012,
    "name": "神话编织者",
    "description": "龙翼的阴影、神祇的低语，你三次亲历神话的篇章，命运在你的足迹上烙印符文。",
    "grade": 3,
    "hide": 0,
    "condition": "MYTHC >= 3"
  },
  "92013": {
    "id": 92013,
    "name": "倾城之貌",
    "description": "你的容颜令月亮羞怯，令精灵为之驻足。颜值冠绝埃尔德兰。",
    "grade": 1,
    "hide": 0,
    "condition": "HCHR > 120"
  },
  "92014": {
    "id": 92014,
    "name": "大贤者",
    "description": "星穹的秘密向你敞开，魔法学院的贤者们尊你为同行。",
    "grade": 1,
    "hide": 0,
    "condition": "HINT > 120"
  },
  "92015": {
    "id": 92015,
    "name": "战神的血脉",
    "description": "你的身躯比龙鳞更坚韧，无论刀剑还是岁月都无法在你身上留下痕迹。",
    "grade": 2,
    "hide": 0,
    "condition": "HSTR > 150"
  },
  "92016": {
    "id": 92016,
    "name": "金库之主",
    "description": "矮人的宝库在你面前黯然失色，你的金币足以买下一座王国。",
    "grade": 2,
    "hide": 0,
    "condition": "HMNY > 200"
  },
  "92017": {
    "id": 92017,
    "name": "永恒的狂喜",
    "description": "你的心灵抵达了极乐净土，尘世再无烦忧能够侵扰。",
    "grade": 2,
    "hide": 0,
    "condition": "HSPR > 150"
  },
  "92018": {
    "id": 92018,
    "name": "命运之眷顾",
    "description": "诸神为你擘画轨迹，命运之线在你手中编织成璀璨的织锦。",
    "grade": 3,
    "hide": 0,
    "condition": "FDLV >= 5"
  },
  "92019": {
    "id": 92019,
    "name": "愚者的奇迹",
    "description": "智力低微？不，那是神选之人的羔羊面纱。你以愚者之姿，触碰了神话。",
    "grade": 2,
    "hide": 1,
    "condition": "HINT <= 30 AND MYTHC >= 1"
  },
  "92020": {
    "id": 92020,
    "name": "新兵报到",
    "description": "你第一次推开公会吱嘎作响的橡木大门，炉火的暖意和羊皮纸的油墨味迎面扑来——从此，你的名字被刻在了冒险者的名册上。",
    "grade": 0,
    "hide": 0,
    "condition": "HSTR >= 15"
  },
  "92021": {
    "id": 92021,
    "name": "地下城征服者",
    "description": "当潮湿的洞穴深处传来最后一声怪物的哀嚎，你踩着碎石与残骸走出，阳光刺破幽暗——地下城已在你脚下臣服。",
    "grade": 1,
    "hide": 0,
    "condition": "MYTHC >= 1"
  },
  "92022": {
    "id": 92022,
    "name": "奥秘学者",
    "description": "在魔法学院的高塔之巅，你解读了禁断的卷轴，元素在你指尖凝成火焰——知识，是你手中最锋利的剑。",
    "grade": 1,
    "hide": 0,
    "condition": "HINT >= 60"
  },
  "92023": {
    "id": 92023,
    "name": "骑士册封",
    "description": "跪于古老的石板地面，长剑轻触你的双肩，国王的声音回荡在圣堂——‘起身吧，骑士。’从此，你的盾牌承载荣耀。",
    "grade": 2,
    "hide": 0,
    "condition": "HCHR >= 50 AND HSTR >= 50"
  },
  "92024": {
    "id": 92024,
    "name": "巨龙之陨",
    "description": "当那遮天蔽日的双翼最后坠入火山口，你站在龙血浸染的灰烬中，握紧了仍在嗡鸣的屠龙剑——一首史诗就此谱写。",
    "grade": 3,
    "hide": 1,
    "condition": "MYTHC >= 3"
  },
  "92025": {
    "id": 92025,
    "name": "诸神的宠儿",
    "description": "神像的眼中流下金色的泪，你被圣光笼罩，耳边响起远古的低语——你已不是凡人，而是神选的代行者。",
    "grade": 3,
    "hide": 1,
    "condition": "HSPR >= 85"
  },
  "92026": {
    "id": 92026,
    "name": "富可敌国",
    "description": "你的金库堆满了矮人的秘银和贵族的珠宝，商人在你的名下颤抖——财富，成了你最坚实的城墙。",
    "grade": 1,
    "hide": 0,
    "condition": "HMNY >= 10000"
  },
  "92027": {
    "id": 92027,
    "name": "永生者",
    "description": "一个世纪的霜雪染白了你的须发，你坐在酒馆的角落，那些曾与你并肩的英雄已化作歌谣，而你仍在举杯，等待下一个黎明的冒险。",
    "grade": 2,
    "hide": 0,
    "condition": "HAGE >= 100"
  },
  "92028": {
    "id": 92028,
    "name": "命运征服者",
    "description": "命运三女神的纺线在你的指尖崩断，无数个十字路口你选择了最不可能的道路——如今，连星辰都为你改道。",
    "grade": 2,
    "hide": 1,
    "condition": "SUM >= 50"
  },
  "92029": {
    "id": 92029,
    "name": "传奇缔造者",
    "description": "吟游诗人传唱你的名号，学者在你的传记边写满注释，孩童模仿你的招式——你不再是人，是一段活着的传说。",
    "grade": 2,
    "hide": 1,
    "condition": "MYTHC >= 5"
  },
  "92030": {
    "id": 92030,
    "name": "初踏征途",
    "description": "第一次踏入冒险者公会的大厅，感受到命运齿轮的转动。",
    "grade": 0,
    "hide": 0,
    "condition": "HINT >= 1"
  },
  "92031": {
    "id": 92031,
    "name": "屠龙者",
    "description": "于古龙峰巅斩杀一头成年巨龙，龙血浸染的剑刃宣告传奇的开端。",
    "grade": 3,
    "hide": 0,
    "condition": "MYTHC >= 1"
  },
  "92032": {
    "id": 92032,
    "name": "大法师之证",
    "description": "在魔法学院的高塔上通过九环考验，奥术辉光如星辰加身。",
    "grade": 2,
    "hide": 0,
    "condition": "HINT >= 80"
  },
  "92033": {
    "id": 92033,
    "name": "传说之终",
    "description": "寿终正寝，墓碑铭刻着你波澜壮阔的一生，吟游诗人传唱不衰。",
    "grade": 3,
    "hide": 1,
    "condition": "HAGE >= 80 AND SUM(MYTHC) >= 5"
  },
  "92034": {
    "id": 92034,
    "name": "遍体鳞伤",
    "description": "在冒险中累计受伤超过百次，疤痕是活着的勋章。",
    "grade": 1,
    "hide": 0,
    "condition": "SUM(FDLV) >= 100"
  },
  "92035": {
    "id": 92035,
    "name": "极乐狂欢",
    "description": "在永恒狂欢节赢得九轮赌局，醉倒在神祇的酒杯里。",
    "grade": 1,
    "hide": 0,
    "condition": "HSPR >= 99"
  },
  "92036": {
    "id": 92036,
    "name": "神选之人",
    "description": "被命运三女神同时垂青，获得改写世界线的权柄。",
    "grade": 3,
    "hide": 1,
    "condition": "MYTHC >= 3"
  },
  "92037": {
    "id": 92037,
    "name": "隐于市井",
    "description": "放弃所有声望，以凡人之躯度过安稳而温暖的一生。",
    "grade": 0,
    "hide": 1,
    "condition": "HCHR = 0 AND HINT = 0 AND HSTR = 0 AND HAGE >= 60"
  },
  "92038": {
    "id": 92038,
    "name": "初出茅庐",
    "description": "你第一次握紧剑柄，踏入冒险者公会，在任务板上留下了你的名字。冒险之途就此展开。",
    "grade": 0,
    "hide": 0,
    "condition": "FDLV >= 1"
  },
  "92039": {
    "id": 92039,
    "name": "双修智者",
    "description": "你的智慧与力量并重，魔法与剑术在你手中相得益彰，成为战场上令人敬畏的战术大师。",
    "grade": 1,
    "hide": 0,
    "condition": "HINT >= 12 AND HSTR >= 12"
  },
  "92040": {
    "id": 92040,
    "name": "财富之巅",
    "description": "你积累的财富足以买下一座小王国，商人们低声传颂着你的慷慨与精明。",
    "grade": 2,
    "hide": 0,
    "condition": "HMNY >= 50"
  },
  "92041": {
    "id": 92041,
    "name": "不死传奇",
    "description": "你经历数十次生死搏杀，却总能从冥界边缘挣扎归来。死亡拒绝对你张开怀抱。",
    "grade": 2,
    "hide": 0,
    "condition": "HAGE >= 70 AND HSTR >= 15"
  },
  "92042": {
    "id": 92042,
    "name": "龙之屠戮者",
    "description": "古老红龙的咆哮没能吓退你，你以凡人之躯斩下它的头颅，龙血染红了整片荒原。你的名字镌刻在史诗之石上。",
    "grade": 3,
    "hide": 0,
    "condition": "MYTHC >= 3 AND HSTR >= 25"
  },
  "92043": {
    "id": 92043,
    "name": "诸神眷顾",
    "description": "你被至少一位神明选中，在圣光中接受祝福，圣痕在你额头闪耀，你成为了神在凡间的代行者。",
    "grade": 3,
    "hide": 1,
    "condition": "MYTHC >= 5 AND HSPR >= 20"
  },
  "92044": {
    "id": 92044,
    "name": "深渊征服者",
    "description": "你深入禁忌的地下城最底层，击败了盘踞千年的古老邪恶。黑暗在你身后崩溃，光明重新照耀。",
    "grade": 3,
    "hide": 1,
    "condition": "FDLV >= 20 AND MYTHC >= 2"
  },
  "92045": {
    "id": 92045,
    "name": "魔法贤者",
    "description": "你参透了魔法的至理，掌握了失传的禁咒，魔法学院的院长们也要向你请教。",
    "grade": 2,
    "hide": 0,
    "condition": "HINT >= 25 AND MYTHC >= 1"
  },
  "92046": {
    "id": 92046,
    "name": "万民敬仰",
    "description": "你的善行与功绩被万民传颂，每个城市都有你的雕像，孩子们吟唱着你的英雄诗篇。",
    "grade": 1,
    "hide": 0,
    "condition": "HSPR >= 15 AND HMNY >= 20 AND HCHR >= 12"
  },
  "92047": {
    "id": 92047,
    "name": "悲剧英雄",
    "description": "你曾拥有至高荣耀，最终却在孤独中逝去，无人知晓你的下落，只有风还在低语你的名字。",
    "grade": 1,
    "hide": 1,
    "condition": "HAGE >= 80 AND HSPR <= 5"
  },
  "92048": {
    "id": 92048,
    "name": "终焉之眠",
    "description": "你的生命跨越百年，见证了数个王朝的兴衰。当死亡终于带走了你，诸神于云端为你摆下宴席。",
    "grade": 3,
    "hide": 0,
    "condition": "HAGE >= 100"
  },
  "92049": {
    "id": 92049,
    "name": "神话编织者",
    "description": "命运之弦在你的指尖颤动。你屡次改写传说，世界将传唱你的名，直至星辰熄灭。",
    "grade": 3,
    "hide": 0,
    "condition": "MYTHC >= 5"
  },
  "92050": {
    "id": 92050,
    "name": "魅惑之瞳",
    "description": "你的容颜如精灵之裁，凡尘不能掩其华。一瞥之间，君王卸甲，恶龙低眉。",
    "grade": 1,
    "hide": 0,
    "condition": "HCHR >= 95"
  },
  "92051": {
    "id": 92051,
    "name": "永烁之辉",
    "description": "你的智慧照亮了埃尔德兰最幽深的角落。奥术学院将你的名字镌刻在穹顶之上，与初代圣贤并列。",
    "grade": 2,
    "hide": 0,
    "condition": "HINT >= 95"
  },
  "92052": {
    "id": 92052,
    "name": "不屈铁壁",
    "description": "你的身躯如同山巅的龙钢，大地都因你的脚步而震颤。千军万马之前，你独自屹立。",
    "grade": 2,
    "hide": 0,
    "condition": "HSTR >= 95"
  },
  "92053": {
    "id": 92053,
    "name": "黄金血脉",
    "description": "金瀑流淌过你的指隙，你坐拥的财富堪比一个王国。大陆上每一枚金币都曾聆听你的名号。",
    "grade": 1,
    "hide": 0,
    "condition": "HMNY >= 99999"
  },
  "92054": {
    "id": 92054,
    "name": "极乐飞升",
    "description": "你的灵魂溢满了纯粹的喜乐，仿佛神国信标，连天使亦为你歌唱。",
    "grade": 1,
    "hide": 0,
    "condition": "HSPR >= 100"
  },
  "92055": {
    "id": 92055,
    "name": "命运之主",
    "description": "你已攀至命运长阶的顶端，俯瞰众生沉浮。诸界在你面前展开，如一本摊开的古卷。",
    "grade": 3,
    "hide": 0,
    "condition": "FDLV >= 10"
  },
  "92056": {
    "id": 92056,
    "name": "双魂之刃",
    "description": "你同时精通剑术与咒法，是千年来唯一的魔武至尊。战场上的光与影，皆为你双生的仆从。",
    "grade": 2,
    "hide": 0,
    "condition": "HSTR >= 80 AND HINT >= 80"
  },
  "92057": {
    "id": 92057,
    "name": "陨落的流星",
    "description": "你在最绚烂的年华猝然消逝，却留下不朽的传奇。诸神为你叹息，将你的灵魂藏入晨星。",
    "grade": 3,
    "hide": 1,
    "condition": "HAGE < 20 AND MYTHC >= 3"
  },
  "92058": {
    "id": 92058,
    "name": "神话初现",
    "description": "你触碰到了那些曾在史诗中传唱的力量，命运的齿轮开始转动。",
    "grade": 0,
    "hide": 0,
    "condition": "MYTHC >= 1"
  },
  "92059": {
    "id": 92059,
    "name": "贤者之颅",
    "description": "你的智慧足以媲美奥术学院的导师，凡人难以理解的秘法在你眼中清澈如泉。",
    "grade": 1,
    "hide": 0,
    "condition": "HINT >= 90"
  },
  "92060": {
    "id": 92060,
    "name": "钢铁血脉",
    "description": "你的身体如同被矮人铁匠千锤百炼的铠甲，刀剑与疾病都难以撼动。",
    "grade": 1,
    "hide": 0,
    "condition": "HSTR >= 90"
  },
  "92061": {
    "id": 92061,
    "name": "神祇之貌",
    "description": "你的容貌已超凡脱俗，连星界的美神都会投来嫉妒的目光。",
    "grade": 1,
    "hide": 0,
    "condition": "HCHR >= 90"
  },
  "92062": {
    "id": 92062,
    "name": "黄金律法",
    "description": "你拥有的金币足以买下一座城邦，冒险者公会账房为你单独开设金库。",
    "grade": 2,
    "hide": 0,
    "condition": "HMNY >= 10000"
  },
  "92063": {
    "id": 92063,
    "name": "世纪守望者",
    "description": "你穿越了一个世纪的烟火与战歌，漫长的寿命使你成为活着的传说。",
    "grade": 2,
    "hide": 0,
    "condition": "HAGE >= 100"
  },
  "92064": {
    "id": 92064,
    "name": "乐土之心",
    "description": "无论面对巨龙还是神祇，你的嘴角永远挂着那抹云淡风轻的笑意。",
    "grade": 0,
    "hide": 1,
    "condition": "HSPR >= 90"
  },
  "92065": {
    "id": 92065,
    "name": "命运咏叹",
    "description": "你不是神话的旁观者，而是亲手将传说撰写在星云之上的诗人。",
    "grade": 3,
    "hide": 0,
    "condition": "MYTHC >= 3"
  },
  "92066": {
    "id": 92066,
    "name": "埃尔德兰之冠",
    "description": "你站在凡人命运的顶峰，连诸神都要聆听你的名字。",
    "grade": 3,
    "hide": 0,
    "condition": "FDLV >= 10"
  },
  "92067": {
    "id": 92067,
    "name": "全能之证",
    "description": "你的天赋均衡而卓越，在美丽、智慧、体魄与灵魂中达到了凡人难以企及的和谐。",
    "grade": 2,
    "hide": 0,
    "condition": "SUM(HCHR, HINT, HSTR, HSPR) >= 320"
  },
  "92068": {
    "id": 92068,
    "name": "初入殿堂",
    "description": "你第一次踏进冒险者公会的大厅，壁炉的火光映照着无数传奇的徽章，命运之轮由此转动。",
    "grade": 0,
    "hide": 0,
    "condition": "FDLV >= 1"
  },
  "92069": {
    "id": 92069,
    "name": "屠龙者",
    "description": "当龙息燃尽天际，你的剑穿透鳞甲，龙的哀嚎响彻山谷——你成了史诗，也成了恐惧。",
    "grade": 3,
    "hide": 1,
    "condition": "MYTHC >= 3"
  },
  "92070": {
    "id": 92070,
    "name": "黄金之触",
    "description": "在永夜迷宫的深处，你解开了矮人王的财宝谜锁，黄金如瀑布倾泻，王国为之震动。",
    "grade": 1,
    "hide": 0,
    "condition": "HMNY >= 5000"
  },
  "92071": {
    "id": 92071,
    "name": "贤者之冠",
    "description": "大图书馆的秘仪认你为主，无穷知识涌入脑海，连诸神都低声私语你的名字。",
    "grade": 2,
    "hide": 0,
    "condition": "HINT >= 120"
  },
  "92072": {
    "id": 92072,
    "name": "不灭之躯",
    "description": "你从死神的镰刀下归来，伤痕累累却屹立不倒，生命如青铜般坚韧。",
    "grade": 1,
    "hide": 0,
    "condition": "HSTR >= 100 AND SUM >= 3"
  },
  "92073": {
    "id": 92073,
    "name": "命运宠儿",
    "description": "幸运女神为你掀开裙角，你接连躲过三次必死的厄运，众人称你为天选者。",
    "grade": 2,
    "hide": 0
  },
  "92074": {
    "id": 92074,
    "name": "骑士的誓言",
    "description": "在蔷薇王庭，你单膝跪地接受册封，从此荣耀即吾命，剑锋所向皆为公正。",
    "grade": 1,
    "hide": 0,
    "condition": "HCHR >= 60 AND HSTR >= 80"
  },
  "92075": {
    "id": 92075,
    "name": "奥秘编织者",
    "description": "你同时驾驭三道禁忌法术的大成，魔网在你指尖颤抖，院长也露出惊惧的目光。",
    "grade": 2,
    "hide": 1,
    "condition": "HINT >= 100 AND MYTHC >= 1"
  },
  "92076": {
    "id": 92076,
    "name": "流浪的国王",
    "description": "你抛弃了王座，隐入荒野，但你的名号仍是各国宴席上的禁忌传说。",
    "grade": 3,
    "hide": 1,
    "condition": "HAGE >= 90 AND HMNY >= 10000 AND HCHR <= 30"
  },
  "92077": {
    "id": 92077,
    "name": "终幕",
    "description": "你抵达了命运档案馆的尽头，所有故事在此终结，所有开始由此新生。",
    "grade": 3,
    "hide": 1,
    "condition": "HAGE >= 100"
  }
}